qanon_mcp/__init__.py
qanon_mcp/posts.json
mseep_pypi_publish_49e8e82122f247c6b62edef23c48241e-0.3.0.dist-info/METADATA
mseep_pypi_publish_49e8e82122f247c6b62edef23c48241e-0.3.0.dist-info/WHEEL
mseep_pypi_publish_49e8e82122f247c6b62edef23c48241e-0.3.0.dist-info/entry_points.txt
mseep_pypi_publish_49e8e82122f247c6b62edef23c48241e-0.3.0.dist-info/licenses/LICENSE.md
mseep_pypi_publish_49e8e82122f247c6b62edef23c48241e-0.3.0.dist-info/RECORD
