Metadata-Version: 2.4
Name: mseep-pypi_publish_49e8e82122f247c6b62edef23c48241e
Version: 0.3.0
Summary: MCP server for QAnon drops for sociological research
Author-email: Jack Kingsman <jack@jackkingsman.me>
License-Expression: MIT
License-File: LICENSE.md
Requires-Python: >=3.10
Requires-Dist: mcp[cli]>=1.6.0
